{"errors":[],"warnings":[],"namedChunkGroups":{"app":{"chunks":[10,2,9,3,4],"assets":["webpack-runtime-9eb071558764c79ec461.js","webpack-runtime-9eb071558764c79ec461.js.map","styles.ef8d318eb58165f52135.css","styles-2d82ac8e3afc0c213061.js","styles-2d82ac8e3afc0c213061.js.map","framework-93d3a746c3cf42acdafc.js","framework-93d3a746c3cf42acdafc.js.map","484bcb1e-d1dcf65b4bd0cfb44aeb.js","484bcb1e-d1dcf65b4bd0cfb44aeb.js.map","app-a4c93f75a1bd50d6adc6.js","app-a4c93f75a1bd50d6adc6.js.map"],"children":{},"childAssets":{}},"component---src-pages-404-js":{"chunks":[0,1,5],"assets":["05d954cf-674dca34b34a38586e4b.js","05d954cf-674dca34b34a38586e4b.js.map","commons-1e663f6daca1dd91eb25.js","commons-1e663f6daca1dd91eb25.js.map","component---src-pages-404-js-19e697cbe5f604382137.js","component---src-pages-404-js-19e697cbe5f604382137.js.map"],"children":{},"childAssets":{}},"component---src-pages-contact-js":{"chunks":[2,0,1,6],"assets":["styles.ef8d318eb58165f52135.css","styles-2d82ac8e3afc0c213061.js","styles-2d82ac8e3afc0c213061.js.map","05d954cf-674dca34b34a38586e4b.js","05d954cf-674dca34b34a38586e4b.js.map","commons-1e663f6daca1dd91eb25.js","commons-1e663f6daca1dd91eb25.js.map","component---src-pages-contact-js-cfb304177489b6e48a1a.js","component---src-pages-contact-js-cfb304177489b6e48a1a.js.map"],"children":{},"childAssets":{}},"component---src-pages-index-js":{"chunks":[2,0,1,7],"assets":["styles.ef8d318eb58165f52135.css","styles-2d82ac8e3afc0c213061.js","styles-2d82ac8e3afc0c213061.js.map","05d954cf-674dca34b34a38586e4b.js","05d954cf-674dca34b34a38586e4b.js.map","commons-1e663f6daca1dd91eb25.js","commons-1e663f6daca1dd91eb25.js.map","component---src-pages-index-js-441f6517db1ee021c94f.js","component---src-pages-index-js-441f6517db1ee021c94f.js.map"],"children":{},"childAssets":{}},"component---src-pages-thank-you-js":{"chunks":[0,1,8],"assets":["05d954cf-674dca34b34a38586e4b.js","05d954cf-674dca34b34a38586e4b.js.map","commons-1e663f6daca1dd91eb25.js","commons-1e663f6daca1dd91eb25.js.map","component---src-pages-thank-you-js-6e4486d5d0fe0cd17bc6.js","component---src-pages-thank-you-js-6e4486d5d0fe0cd17bc6.js.map"],"children":{},"childAssets":{}}},"assetsByChunkName":{"app":["webpack-runtime-9eb071558764c79ec461.js","styles.ef8d318eb58165f52135.css","styles-2d82ac8e3afc0c213061.js","framework-93d3a746c3cf42acdafc.js","484bcb1e-d1dcf65b4bd0cfb44aeb.js","app-a4c93f75a1bd50d6adc6.js"],"component---src-pages-404-js":["05d954cf-674dca34b34a38586e4b.js","commons-1e663f6daca1dd91eb25.js","component---src-pages-404-js-19e697cbe5f604382137.js"],"component---src-pages-contact-js":["styles.ef8d318eb58165f52135.css","styles-2d82ac8e3afc0c213061.js","05d954cf-674dca34b34a38586e4b.js","commons-1e663f6daca1dd91eb25.js","component---src-pages-contact-js-cfb304177489b6e48a1a.js"],"component---src-pages-index-js":["styles.ef8d318eb58165f52135.css","styles-2d82ac8e3afc0c213061.js","05d954cf-674dca34b34a38586e4b.js","commons-1e663f6daca1dd91eb25.js","component---src-pages-index-js-441f6517db1ee021c94f.js"],"component---src-pages-thank-you-js":["05d954cf-674dca34b34a38586e4b.js","commons-1e663f6daca1dd91eb25.js","component---src-pages-thank-you-js-6e4486d5d0fe0cd17bc6.js"]}}